LICENSE.txt
MANIFEST.in
README.rst
bootstrap-buildout.py
buildout-with-csu.cfg
buildout.cfg
requirements.txt
setup.py
version.txt
doc/baselines.rst
doc/conf.py
doc/contribute.rst
doc/evaluate.rst
doc/experiments.rst
doc/index.rst
doc/installation.rst
doc/links.rst
doc/manual_databases.rst
doc/manual_features.rst
doc/manual_preprocessors.rst
doc/manual_tools.rst
doc/manual_utils.rst
doc/references.rst
doc/satellite.rst
doc/specialized.rst
doc/img/CMC.png
doc/img/DET.png
doc/img/ROC.png
doc/img/logo.png
facereclib/__init__.py
facereclib.egg-info/PKG-INFO
facereclib.egg-info/SOURCES.txt
facereclib.egg-info/dependency_links.txt
facereclib.egg-info/entry_points.txt
facereclib.egg-info/not-zip-safe
facereclib.egg-info/requires.txt
facereclib.egg-info/top_level.txt
facereclib/configurations/__init__.py
facereclib/configurations/databases/__init__.py
facereclib/configurations/databases/arface.py
facereclib/configurations/databases/atnt.py
facereclib/configurations/databases/banca.py
facereclib/configurations/databases/banca_twothirds.py
facereclib/configurations/databases/caspeal.py
facereclib/configurations/databases/frgc.py
facereclib/configurations/databases/gbu.py
facereclib/configurations/databases/lfw_restricted.py
facereclib/configurations/databases/lfw_unrestricted.py
facereclib/configurations/databases/mobio.py
facereclib/configurations/databases/mobio_female.py
facereclib/configurations/databases/mobio_male.py
facereclib/configurations/databases/multipie.py
facereclib/configurations/databases/multipie_P.py
facereclib/configurations/databases/multipie_P110.py
facereclib/configurations/databases/scface.py
facereclib/configurations/databases/xm2vts.py
facereclib/configurations/features/__init__.py
facereclib/configurations/features/dct_blocks.py
facereclib/configurations/features/eigenfaces.py
facereclib/configurations/features/grid_graph.py
facereclib/configurations/features/grid_graph_aligned.py
facereclib/configurations/features/lgbphs.py
facereclib/configurations/features/linearize.py
facereclib/configurations/features/sift_bob_keypoints.py
facereclib/configurations/features/sift_keypoints.py
facereclib/configurations/grid/__init__.py
facereclib/configurations/grid/demanding.py
