Metadata-Version: 1.1
Name: facereclib
Version: 2.1.2
Summary: Compare a variety of face recognition algorithms by running them on many image databases with default protocols.
Home-page: http://github.com/idiap/facereclib
Author: Manuel Guenther
Author-email: manuel.guenther@idiap.ch
License: LICENSE.txt
Keywords: Face recognition,face verification,reproducible research,algorithm evaluation
Platform: UNKNOWN
Classifier: Framework :: Bob
Classifier: Development Status :: 4 - Beta
Classifier: Intended Audience :: Science/Research
Classifier: License :: OSI Approved :: GNU General Public License v3 (GPLv3)
Classifier: Natural Language :: English
Classifier: Programming Language :: Python
Classifier: Programming Language :: Python :: 2.7
Classifier: Environment :: Console
Classifier: Framework :: Buildout
Classifier: Topic :: Scientific/Engineering
